sldap3/make_daemon.py
sldap3/make_service.py
sldap3/version.py
sldap3/__init__.py
sldap3/backend/__init__.py
sldap3/backend/user/json.py
sldap3/backend/user/__init__.py
sldap3/core/dsa.py
sldap3/core/dua.py
sldap3/core/instance.py
sldap3/core/mock_dsa.py
sldap3/core/user.py
sldap3/core/__init__.py
sldap3/operation/bind.py
sldap3/operation/extended.py
sldap3/operation/unbind.py
sldap3/operation/__init__.py
sldap3/protocol/rfc4511.py
sldap3/protocol/__init__.py
sldap3/utils/__init__.py
sldap3-0.0.4a0.dist-info/DESCRIPTION.rst
sldap3-0.0.4a0.dist-info/METADATA
sldap3-0.0.4a0.dist-info/metadata.json
sldap3-0.0.4a0.dist-info/RECORD
sldap3-0.0.4a0.dist-info/top_level.txt
sldap3-0.0.4a0.dist-info/WHEEL
