Metadata-Version: 2.0
Name: sldap3
Version: 0.0.4a0
Summary: A strictly RFC 4511 conforming LDAP V3 pure Python server. Same codebase for Python 2, Python3, PyPy and PyPy 3
Home-page: https://github.com/cannatag/sldap3
Author: Giovanni Cannata
Author-email: cannatag@gmail.com
License: LGPL v3
Keywords: python3 python2 ldap server
Platform: UNKNOWN
Classifier: Development Status :: 2 - Pre-Alpha
Classifier: Intended Audience :: Developers
Classifier: Intended Audience :: System Administrators
Classifier: Operating System :: MacOS :: MacOS X
Classifier: Operating System :: Microsoft :: Windows
Classifier: Operating System :: POSIX :: Linux
Classifier: License :: OSI Approved :: GNU Lesser General Public License v3 (LGPLv3)
Classifier: Programming Language :: Python
Classifier: Programming Language :: Python :: 2
Classifier: Programming Language :: Python :: 3
Classifier: Topic :: Software Development :: Libraries :: Python Modules
Classifier: Topic :: System :: Systems Administration :: Authentication/Directory :: LDAP
Requires-Dist: pyasn1 (>=0.1.7)
Requires-Dist: ldap3 (>=0.9.8.2)
